MANIFEST.in
README.md
setup.cfg
setup.py
./scripts/lif
lif/__init__.py
lif/__main__.py
lif/cpp_vector.pxd
lif/cython_api.cpp
lif/cython_api.pyx
lif.egg-info/PKG-INFO
lif.egg-info/SOURCES.txt
lif.egg-info/dependency_links.txt
lif.egg-info/top_level.txt
lif/__pycache__/__init__.cpython-37.pyc
lif/__pycache__/__main__.cpython-37.pyc
lif/cpp_code/algorithms_interface.cpp
lif/cpp_code/algorithms_interface.hpp
lif/cpp_code/algorithms/pollards_rho_algorithm.cpp
lif/cpp_code/algorithms/pollards_rho_algorithm.hpp
lif/cpp_code/algorithms/trial_division_algorithm.cpp
lif/cpp_code/algorithms/trial_division_algorithm.hpp
lif/cpp_code/bigint/bigint.cpp
lif/cpp_code/bigint/fft.cpp
lif/cpp_code/bigint/fft.hpp