Metadata-Version: 1.1
Name: lif
Version: 0.1.9
Summary: Lif lib
Home-page: https://github.com/yonlif/lif
Author: Yonlif & Eilonlif
Author-email: yonlif@gmail.com
License: MIT
Download-URL: https://github.com/yonlif/lif/archive/refs/tags/0.1.9.tar.gz
Keywords: Large,Integer,Factorization,Lif
Platform: UNKNOWN
Classifier: Development Status :: 3 - Alpha
Classifier: Intended Audience :: Developers
Classifier: Topic :: Software Development :: Build Tools
Classifier: License :: OSI Approved :: MIT License
Classifier: Programming Language :: Python :: 3.6
